secots.py
secots-0.1.1.dist-info/METADATA
secots-0.1.1.dist-info/WHEEL
secots-0.1.1.dist-info/licenses/LICENSE
secots-0.1.1.dist-info/RECORD
