Metadata-Version: 2.3
Name: secots
Version: 0.1.1
Summary: Calculate the smallest enclosing circle of a point cloud on a (hemi)sphere in linear time with a Welzl-type algorithm.
Project-URL: Documentation, https://github.com/jeflem/secots/blob/main/README.md
Project-URL: Repository, https://github.com/jeflem/secots.git
Project-URL: Issues, https://github.com/jeflem/secots/issues
Project-URL: Changelog, https://github.com/jeflem/secots/blob/master/CHANGELOG.md
Author-email: Jens Flemming <jens.flemming@fh-zwickau.de>
Maintainer-email: Jens Flemming <jens.flemming@fh-zwickau.de>
License:                     GNU GENERAL PUBLIC LICENSE
License-File: LICENSE
Keywords: Welzl,hemisphere,point cloud,smallest enclosing circle,sphere
Requires-Dist: numpy
